Workbook

Sheet WBS
A1: › WORK BREAKDOWN STRUCTURE — PROGETTO DI ASSESSMENT GO-TO-MARKET
A2: LEGENDA — Le colonne con intestazione GIALLA sono da compilare a mano: le loro celle portano un riquadro nero. Le celle su fondo GRIGIO sono calcolate da formula e non vanno modificate. Tariffe e ore per giornata si impostano nel foglio «Parametri», i nomi del team nel foglio «Ruoli».
A3: Le colonne «gg Front office / Back office / Viaggio» esprimono GIORNATE-UOMO aggregate, non giorni di calendario: 2 consulenti per mezza giornata dal cliente = 1 giornata front. La composizione della squadra si descrive nella colonna «Delivery». Le ore di viaggio sono incluse nel monte ore.
A5: # | B5: Cod. WBS | C5: Fase | D5: Tipo | E5: Modalità | F5: Blocco | G5: Sett. inizio | H5: Durata (sett.) | I5: Sett. fine | J5: Descrizione | K5: Attività preparatorie | L5: Attività di follow-up | M5: Input dal cliente | N5: Output / Deliverable | O5: Owner | P5: Partecipanti | Q5: N. incontri | R5: Durata incontro (h) | S5: gg Front office | T5: gg Back office | U5: gg Viaggio | V5: Delivery (composizione team) | W5: Tot. giornate | X5: Ore totali | Y5: Costo totale | Z5: Note
A6: 1 | B6: 1.1 | C6: Kick off e raccolta dati | D6: Cliente | E6: Remoto | F6: 1 · Avvio | G6: 1 | H6: 1 | I6: =IF(AND(G6<>"",H6<>""),G6+H6-1,"") | J6: Incontro di avvio in remoto con i team di progetto di entrambe le parti. Si condividono obiettivi e perimetro dell'assessment, si presenta il team e si calendarizzano gli incontri successivi. Nella seconda parte si illustra la struttura dei dati richiesta al cliente, si chiariscono dubbi e domande e si concorda la data di consegna degli export, fissata entro una settimana dal kick off. Il lead time della fase coincide con il tempo necessario al cliente per predisporre e trasmettere gli export. | K6: Invio dell'invito e fissaggio dell'incontro a cura del Commerciale. | L6: Invio, a cura del Project Manager, del documento presentato e del tracciato dei dati richiesti. | M6: Export dei dati trasmessi via email entro 5 giorni lavorativi dal kick off. | N6: Obiettivi e perimetro condivisi · calendario degli incontri · tracciato dati concordato. | O6: Commerciale (convocazione) → Project Manager (follow-up) | P6: Team di progetto completo, entrambe le parti | Q6: 1 | W6: =IF(COUNT(S6:U6)=0,"",SUM(S6:U6)) | X6: =IF(W6="","",W6*Parametri!$C$5) | Y6: =IF(COUNT(S6:U6)=0,"",S6*Parametri!$C$5*Parametri!$C$6+T6*Parametri!$C$5*Parametri!$C$7+U6*Parametri!$C$5*Parametri!$C$8) | Z6: Vincolo: la consegna degli export non può superare 1 settimana dal kick off.
A7: 2 | B7: 1.2 | C7: Analisi dati e sintesi | D7: Interna | E7: Interna | F7: 1 · Avvio | G7: 2 | H7: 1 | I7: =IF(AND(G7<>"",H7<>""),G7+H7-1,"") | J7: Analisi degli export ricevuti per ricostruire l'evidenza sulla base clienti attuale, su due piani: lettura logico-funzionale del dato e verifica di data quality. L'esito confluisce in una restituzione interna al team, in cui si presentano le evidenze emerse, l'issue tree e le prime ipotesi da validare nel corso del progetto. | K7: Verifica di completezza e leggibilità degli export ricevuti. | L7: Formalizzazione al cliente via email di dubbi, lacune e richieste di integrazione dati. | M7: Export dati completi e leggibili. | N7: Evidenze sulla base clienti · esiti di data quality · issue tree · ipotesi da validare · lista domande al cliente. | O7: Project Manager | P7: 1 consulente RevOps sull'analisi; restituzione di 1 ora all'intero team | Q7: 1 | R7: 1 | V7: 1 risorsa in back office; restituzione al team di 1 ora con tutto il gruppo | W7: =IF(COUNT(S7:U7)=0,"",SUM(S7:U7)) | X7: =IF(W7="","",W7*Parametri!$C$5) | Y7: =IF(COUNT(S7:U7)=0,"",S7*Parametri!$C$5*Parametri!$C$6+T7*Parametri!$C$5*Parametri!$C$7+U7*Parametri!$C$5*Parametri!$C$8) | Z7: L'analisi è svolta da una sola persona: la restituzione è l'unico momento collegiale.
A8: 3 | B8: 1.3 | C8: Revenue model | D8: Cliente | E8: In presenza | F8: 2 · Workshop in parallelo | G8: 3 | H8: 2 | I8: =IF(AND(G8<>"",H8<>""),G8+H8-1,"") | J8: Workshop in presenza per la mappatura del modello di ricavo del cliente, articolato in due sessioni distinte — una dedicata al canale B2B e una al B2C — con compilazione congiunta del framework revenue model. | K8: Predisposizione dei materiali di workshop e condivisione dell'agenda con il cliente. | L8: Compilazione del file di delivery · restituzione formalizzata al cliente · registrazione delle evidenze emerse. | M8: Disponibilità dei referenti di canale e accesso ai dati di ricavo. | N8: Revenue model mappato e validato per canale B2B e B2C. | O8: Project Manager | P8: Facilitatore senior + 2 consulenti RevOps junior | Q8: 2 | V8: 3 persone in presenza (1 facilitatore senior + 2 consulenti junior) | W8: =IF(COUNT(S8:U8)=0,"",SUM(S8:U8)) | X8: =IF(W8="","",W8*Parametri!$C$5) | Y8: =IF(COUNT(S8:U8)=0,"",S8*Parametri!$C$5*Parametri!$C$6+T8*Parametri!$C$5*Parametri!$C$7+U8*Parametri!$C$5*Parametri!$C$8) | Z8: Durata delle due sessioni da definire.
A9: 4 | B9: 1.4 | C9: ICP model e customer journey | D9: Cliente | E9: Remoto | F9: 2 · Workshop in parallelo | G9: 3 | H9: 2 | I9: =IF(AND(G9<>"",H9<>""),G9+H9-1,"") | J9: Due incontri in remoto — uno sul canale B2B e uno sul B2C — per la definizione del profilo di cliente ideale e della relativa customer journey. La mappatura si sviluppa sul bow tie: per ciascuna fase si individua il percorso desiderato e le frizioni oggi presenti. | K9: Predisposizione della struttura bow tie e condivisione dell'agenda. | L9: Compilazione del file di delivery · restituzione formalizzata al cliente · registrazione delle evidenze emerse. | M9: Disponibilità dei referenti marketing e sales. | N9: Ideal Customer Profile definito · customer journey mappata lungo il bow tie con le frizioni per fase. | O9: Project Manager | P9: Facilitatore senior + 2 consulenti RevOps junior | Q9: 2 | V9: 3 persone in remoto (1 facilitatore senior + 2 consulenti junior) | W9: =IF(COUNT(S9:U9)=0,"",SUM(S9:U9)) | X9: =IF(W9="","",W9*Parametri!$C$5) | Y9: =IF(COUNT(S9:U9)=0,"",S9*Parametri!$C$5*Parametri!$C$6+T9*Parametri!$C$5*Parametri!$C$7+U9*Parametri!$C$5*Parametri!$C$8) | Z9: Durata delle due sessioni da definire.
A10: 5 | B10: 1.5 | C10: Process design | D10: Cliente | E10: In presenza | F10: 2 · Workshop in parallelo | G10: 3 | H10: 2 | I10: =IF(AND(G10<>"",H10<>""),G10+H10-1,"") | J10: Workshop in presenza per la mappatura dei processi attualmente in essere su marketing, sales e delivery. Si analizza cosa funziona e cosa non funziona nei flussi correnti e si individuano i gap rispetto allo stato desiderato definito nella customer journey. | K10: Raccolta della documentazione di processo esistente e condivisione dell'agenda. | L10: Compilazione del file di delivery · restituzione formalizzata al cliente · registrazione delle evidenze emerse. | M10: Documentazione di processo e disponibilità dei process owner. | N10: Mappatura del flusso di processo lungo l'intera catena del valore go-to-market · gap rispetto allo stato desiderato. | O10: Project Manager | P10: Facilitatore senior + 2 consulenti RevOps junior | V10: 3 persone in presenza (1 facilitatore senior + 2 consulenti junior) | W10: =IF(COUNT(S10:U10)=0,"",SUM(S10:U10)) | X10: =IF(W10="","",W10*Parametri!$C$5) | Y10: =IF(COUNT(S10:U10)=0,"",S10*Parametri!$C$5*Parametri!$C$6+T10*Parametri!$C$5*Parametri!$C$7+U10*Parametri!$C$5*Parametri!$C$8) | Z10: Numero e durata delle sessioni da definire.
A11: 6 | B11: 1.6 | C11: Tech stack | D11: Cliente | E11: Da definire | F11: 2 · Workshop in parallelo | G11: 3 | H11: 2 | I11: =IF(AND(G11<>"",H11<>""),G11+H11-1,"") | J11: Ricognizione degli strumenti oggi in uso che intercettano la strategia go-to-market, con verifica di come sono strutturati database e flussi di dati. L'obiettivo è fotografare lo stack as-is e disegnare lo stack to-be in ottica di razionalizzazione. | K11: Richiesta preventiva dell'inventario applicativo e delle licenze in essere. | L11: Compilazione del file di delivery · restituzione formalizzata al cliente · registrazione delle evidenze emerse. | M11: Inventario degli strumenti in uso e accesso ai referenti IT. | N11: Mappa degli strumenti as-is e to-be · indicazioni di razionalizzazione dello stack e del database. | O11: Project Manager | P11: Facilitatore senior + 2 consulenti RevOps junior | V11: 3 persone (1 facilitatore senior + 2 consulenti junior) | W11: =IF(COUNT(S11:U11)=0,"",SUM(S11:U11)) | X11: =IF(W11="","",W11*Parametri!$C$5) | Y11: =IF(COUNT(S11:U11)=0,"",S11*Parametri!$C$5*Parametri!$C$6+T11*Parametri!$C$5*Parametri!$C$7+U11*Parametri!$C$5*Parametri!$C$8) | Z11: Modalità (presenza / remoto), numero e durata delle sessioni da definire.
A12: 7 | B12: 1.7 | C12: Data model | D12: Cliente | E12: Da definire | F12: 2 · Workshop in parallelo | G12: 3 | H12: 2 | I12: =IF(AND(G12<>"",H12<>""),G12+H12-1,"") | J12: Incontro dedicato alla proposta del set di KPI necessari a misurare il sistema, costruito utilizzando il bow tie come backbone. Si definiscono KPI di primo e di secondo livello per monitorare l'avanzamento della generazione di valore. | K12: Predisposizione dell'albero dei KPI di primo e secondo livello sul bow tie. | L12: Compilazione del file di delivery · restituzione formalizzata al cliente · registrazione delle evidenze emerse. | M12: Disponibilità dei dati necessari ad alimentare i KPI proposti. | N12: Set di KPI di primo e secondo livello ancorati al bow tie · logica di misurazione della generazione di valore. | O12: Project Manager | P12: Facilitatore senior + 2 consulenti RevOps junior | Q12: 1 | V12: 3 persone (1 facilitatore senior + 2 consulenti junior) | W12: =IF(COUNT(S12:U12)=0,"",SUM(S12:U12)) | X12: =IF(W12="","",W12*Parametri!$C$5) | Y12: =IF(COUNT(S12:U12)=0,"",S12*Parametri!$C$5*Parametri!$C$6+T12*Parametri!$C$5*Parametri!$C$7+U12*Parametri!$C$5*Parametri!$C$8) | Z12: Modalità (presenza / remoto) e durata da definire.
A13: 8 | B13: 1.8 | C13: Interviste qualitative | D13: Cliente | E13: Remoto | F13: 3 · Approfondimento | G13: 5 | H13: 1 | I13: =IF(AND(G13<>"",H13<>""),G13+H13-1,"") | J13: Ciclo di interviste individuali in remoto, condotte da un solo consulente a valle del process design. Sono interviste qualitative volte a raccogliere il punto di vista degli utenti interni sui temi emersi nei workshop e a far emergere frizioni operative non visibili nella mappatura di processo. | K13: Selezione degli intervistati con il cliente e predisposizione della guida di intervista. | L13: Sintesi trasversale delle interviste e integrazione delle frizioni nella mappatura di processo. | M13: Individuazione e disponibilità degli utenti interni da intervistare. | N13: Frizioni operative rilevate · feedback qualitativi sui temi aperti nel process design. | O13: Project Manager | P13: 1 consulente RevOps; referenti operativi lato cliente | V13: 1 persona in remoto | W13: =IF(COUNT(S13:U13)=0,"",SUM(S13:U13)) | X13: =IF(W13="","",W13*Parametri!$C$5) | Y13: =IF(COUNT(S13:U13)=0,"",S13*Parametri!$C$5*Parametri!$C$6+T13*Parametri!$C$5*Parametri!$C$7+U13*Parametri!$C$5*Parametri!$C$8) | Z13: Fase separata perché si svolge a valle dei workshop, con un solo consulente impegnato.
A14: 9 | B14: 1.9 | C14: Sintesi evidenze e business case | D14: Interna | E14: Interna | F14: 4 · Sintesi e validazione | G14: 6 | H14: 1 | I14: =IF(AND(G14<>"",H14<>""),G14+H14-1,"") | J14: Fase interna di ristrutturazione di tutte le evidenze raccolte e di costruzione del piano di lavoro, con elaborazione dei business case a supporto delle iniziative individuate. | K14: Consolidamento dei file di delivery di tutte le fasi precedenti. | L14: Predisposizione dei materiali per la review con il cliente. | N14: Piano di lavoro strutturato · business case per iniziativa. | O14: Project Manager | P14: Team di progetto | W14: =IF(COUNT(S14:U14)=0,"",SUM(S14:U14)) | X14: =IF(W14="","",W14*Parametri!$C$5) | Y14: =IF(COUNT(S14:U14)=0,"",S14*Parametri!$C$5*Parametri!$C$6+T14*Parametri!$C$5*Parametri!$C$7+U14*Parametri!$C$5*Parametri!$C$8)
A15: 10 | B15: 1.10 | C15: Review con il cliente | D15: Cliente | E15: Remoto | F15: 4 · Sintesi e validazione | G15: 7 | H15: 1 | I15: =IF(AND(G15<>"",H15<>""),G15+H15-1,"") | J15: Incontro di validazione con il team di lavoro lato cliente, centrato sui business case costruiti: si verifica l'allineamento su priorità e numeri e si stabilisce se procedere o iterare su specifici ambiti. | K15: Invio anticipato dei business case per lettura preventiva. | L15: Recepimento delle iterazioni richieste e aggiornamento del piano di lavoro. | M15: Presenza dei decisori lato cliente. | N15: Business case validati oppure lista delle iterazioni richieste. | O15: Project Manager | P15: Team di progetto + team di lavoro lato cliente | Q15: 1 | W15: =IF(COUNT(S15:U15)=0,"",SUM(S15:U15)) | X15: =IF(W15="","",W15*Parametri!$C$5) | Y15: =IF(COUNT(S15:U15)=0,"",S15*Parametri!$C$5*Parametri!$C$6+T15*Parametri!$C$5*Parametri!$C$7+U15*Parametri!$C$5*Parametri!$C$8) | Z15: GATE DI PROGETTO: il consolidamento del report parte solo a validazione avvenuta.
A16: 11 | B16: 1.11 | C16: Consolidamento report finale | D16: Interna | E16: Interna | F16: 5 · Chiusura | G16: 8 | H16: 2 | I16: =IF(AND(G16<>"",H16<>""),G16+H16-1,"") | J16: Consolidamento dell'intero assessment nel report finale: stesura delle slide in versione definitiva e valorizzazione economica della roadmap di progetto. | K16: Recepimento degli esiti della review con il cliente. | L16: Condivisione anticipata del report con i referenti prima della presentazione. | N16: Report finale di assessment · roadmap di progetto valorizzata economicamente. | O16: Project Manager | P16: Team di progetto | W16: =IF(COUNT(S16:U16)=0,"",SUM(S16:U16)) | X16: =IF(W16="","",W16*Parametri!$C$5) | Y16: =IF(COUNT(S16:U16)=0,"",S16*Parametri!$C$5*Parametri!$C$6+T16*Parametri!$C$5*Parametri!$C$7+U16*Parametri!$C$5*Parametri!$C$8)
A17: 12 | B17: 1.12 | C17: Presentazione assessment | D17: Cliente | E17: Da definire | F17: 5 · Chiusura | G17: 10 | H17: 1 | I17: =IF(AND(G17<>"",H17<>""),G17+H17-1,"") | J17: Presentazione al cliente del report finale di assessment, della roadmap e della relativa valorizzazione economica, come passaggio di consegna verso la fase successiva. | K17: Allineamento sull'agenda e sui partecipanti lato cliente. | L17: Consegna formale del report e apertura del confronto sulla fase successiva. | M17: Presenza dei decisori lato cliente. | N17: Assessment consegnato · roadmap valorizzata condivisa · next step definiti. | O17: Project Manager | P17: Team di progetto + decisori lato cliente | Q17: 1 | W17: =IF(COUNT(S17:U17)=0,"",SUM(S17:U17)) | X17: =IF(W17="","",W17*Parametri!$C$5) | Y17: =IF(COUNT(S17:U17)=0,"",S17*Parametri!$C$5*Parametri!$C$6+T17*Parametri!$C$5*Parametri!$C$7+U17*Parametri!$C$5*Parametri!$C$8) | Z17: Modalità (presenza / remoto) da definire.
A18: TOTALE PROGETTO | S18: =SUM(S6:S17) | T18: =SUM(T6:T17) | U18: =SUM(U6:U17) | W18: =SUM(W6:W17) | X18: =SUM(X6:X17) | Y18: =SUM(Y6:Y17)
A20: ESEMPIO DI COMPILAZIONE — riga dimostrativa, NON conteggiata nei totali. Mostra il formato atteso per le colonne numeriche.
A21: es. | B21: 1.x | C21: Nome della fase | D21: Cliente | E21: In presenza | F21: 2 · Workshop in parallelo | G21: 3 | H21: 2 | I21: =G21+H21-1 | J21: Descrizione sintetica di cosa avviene nella fase. | K21: Cosa si fa prima. | L21: Cosa si fa dopo. | M21: Cosa serve dal cliente. | N21: Cosa esce dalla fase. | O21: Project Manager | P21: Facilitatore senior + 2 consulenti junior | Q21: 2 | R21: 4 | S21: 1.5 | T21: 2 | U21: 0.5 | V21: 3 persone in presenza, 1 sola lavora in back office | W21: =SUM(S21:U21) | X21: =W21*Parametri!$C$5 | Y21: =S21*Parametri!$C$5*Parametri!$C$6+T21*Parametri!$C$5*Parametri!$C$7+U21*Parametri!$C$5*Parametri!$C$8 | Z21: 1,5 gg front = 3 consulenti per mezza giornata + 3 consulenti per mezza giornata.

Sheet Timeline
A1: › TIMELINE DI PROGETTO — SOVRAPPOSIZIONE DELLE FASI PER SETTIMANA
A2: Le barre si disegnano da sole dalle settimane impostate nella WBS: qui non si scrive nulla. GIALLO = le fasi che si svolgono nelle STESSE settimane, in parallelo. NERO = altra fase con il cliente. GRIGIO = fase interna. La riga in fondo conta quante fasi sono attive in ciascuna settimana.
A4: # | B4: Fase | C4: Tipo | D4: Blocco | E4: Da sett. | F4: A sett. | G4: 1 | H4: 2 | I4: 3 | J4: 4 | K4: 5 | L4: 6 | M4: 7 | N4: 8 | O4: 9 | P4: 10 | Q4: 11 | R4: 12
A5: Settimane con fasi in parallelo › | G5: =IF(G18>1,"›","") | H5: =IF(H18>1,"›","") | I5: =IF(I18>1,"›","") | J5: =IF(J18>1,"›","") | K5: =IF(K18>1,"›","") | L5: =IF(L18>1,"›","") | M5: =IF(M18>1,"›","") | N5: =IF(N18>1,"›","") | ... R5: =IF(R18>1,"›","")
A6: =WBS!A6 | B6: =WBS!C6 | C6: =WBS!D6 | D6: =WBS!F6 | E6: =WBS!G6 | F6: =WBS!I6 | G6: =IF(AND($E6<>"",$F6<>"",$E6<=G$4,$F6>=G$4),1,"") | H6: =IF(AND($E6<>"",$F6<>"",$E6<=H$4,$F6>=H$4),1,"") | I6: =IF(AND($E6<>"",$F6<>"",$E6<=I$4,$F6>=I$4),1,"") | J6: =IF(AND($E6<>"",$F6<>"",$E6<=J$4,$F6>=J$4),1,"") | K6: =IF(AND($E6<>"",$F6<>"",$E6<=K$4,$F6>=K$4),1,"") | L6: =IF(AND($E6<>"",$F6<>"",$E6<=L$4,$F6>=L$4),1,"") | M6: =IF(AND($E6<>"",$F6<>"",$E6<=M$4,$F6>=M$4),1,"") | N6: =IF(AND($E6<>"",$F6<>"",$E6<=N$4,$F6>=N$4),1,"") | ... R6: =IF(AND($E6<>"",$F6<>"",$E6<=R$4,$F6>=R$4),1,"")
A7: =WBS!A7 | B7: =WBS!C7 | C7: =WBS!D7 | D7: =WBS!F7 | E7: =WBS!G7 | F7: =WBS!I7 | G7: =IF(AND($E7<>"",$F7<>"",$E7<=G$4,$F7>=G$4),1,"") | H7: =IF(AND($E7<>"",$F7<>"",$E7<=H$4,$F7>=H$4),1,"") | I7: =IF(AND($E7<>"",$F7<>"",$E7<=I$4,$F7>=I$4),1,"") | J7: =IF(AND($E7<>"",$F7<>"",$E7<=J$4,$F7>=J$4),1,"") | K7: =IF(AND($E7<>"",$F7<>"",$E7<=K$4,$F7>=K$4),1,"") | L7: =IF(AND($E7<>"",$F7<>"",$E7<=L$4,$F7>=L$4),1,"") | M7: =IF(AND($E7<>"",$F7<>"",$E7<=M$4,$F7>=M$4),1,"") | N7: =IF(AND($E7<>"",$F7<>"",$E7<=N$4,$F7>=N$4),1,"") | ... R7: =IF(AND($E7<>"",$F7<>"",$E7<=R$4,$F7>=R$4),1,"")
A8: =WBS!A8 | B8: =WBS!C8 | C8: =WBS!D8 | D8: =WBS!F8 | E8: =WBS!G8 | F8: =WBS!I8 | G8: =IF(AND($E8<>"",$F8<>"",$E8<=G$4,$F8>=G$4),1,"") | H8: =IF(AND($E8<>"",$F8<>"",$E8<=H$4,$F8>=H$4),1,"") | I8: =IF(AND($E8<>"",$F8<>"",$E8<=I$4,$F8>=I$4),1,"") | J8: =IF(AND($E8<>"",$F8<>"",$E8<=J$4,$F8>=J$4),1,"") | K8: =IF(AND($E8<>"",$F8<>"",$E8<=K$4,$F8>=K$4),1,"") | L8: =IF(AND($E8<>"",$F8<>"",$E8<=L$4,$F8>=L$4),1,"") | M8: =IF(AND($E8<>"",$F8<>"",$E8<=M$4,$F8>=M$4),1,"") | N8: =IF(AND($E8<>"",$F8<>"",$E8<=N$4,$F8>=N$4),1,"") | ... R8: =IF(AND($E8<>"",$F8<>"",$E8<=R$4,$F8>=R$4),1,"")
A9: =WBS!A9 | B9: =WBS!C9 | C9: =WBS!D9 | D9: =WBS!F9 | E9: =WBS!G9 | F9: =WBS!I9 | G9: =IF(AND($E9<>"",$F9<>"",$E9<=G$4,$F9>=G$4),1,"") | H9: =IF(AND($E9<>"",$F9<>"",$E9<=H$4,$F9>=H$4),1,"") | I9: =IF(AND($E9<>"",$F9<>"",$E9<=I$4,$F9>=I$4),1,"") | J9: =IF(AND($E9<>"",$F9<>"",$E9<=J$4,$F9>=J$4),1,"") | K9: =IF(AND($E9<>"",$F9<>"",$E9<=K$4,$F9>=K$4),1,"") | L9: =IF(AND($E9<>"",$F9<>"",$E9<=L$4,$F9>=L$4),1,"") | M9: =IF(AND($E9<>"",$F9<>"",$E9<=M$4,$F9>=M$4),1,"") | N9: =IF(AND($E9<>"",$F9<>"",$E9<=N$4,$F9>=N$4),1,"") | ... R9: =IF(AND($E9<>"",$F9<>"",$E9<=R$4,$F9>=R$4),1,"")
A10: =WBS!A10 | B10: =WBS!C10 | C10: =WBS!D10 | D10: =WBS!F10 | E10: =WBS!G10 | F10: =WBS!I10 | G10: =IF(AND($E10<>"",$F10<>"",$E10<=G$4,$F10>=G$4),1,"") | H10: =IF(AND($E10<>"",$F10<>"",$E10<=H$4,$F10>=H$4),1,"") | I10: =IF(AND($E10<>"",$F10<>"",$E10<=I$4,$F10>=I$4),1,"") | J10: =IF(AND($E10<>"",$F10<>"",$E10<=J$4,$F10>=J$4),1,"") | K10: =IF(AND($E10<>"",$F10<>"",$E10<=K$4,$F10>=K$4),1,"") | L10: =IF(AND($E10<>"",$F10<>"",$E10<=L$4,$F10>=L$4),1,"") | M10: =IF(AND($E10<>"",$F10<>"",$E10<=M$4,$F10>=M$4),1,"") | N10: =IF(AND($E10<>"",$F10<>"",$E10<=N$4,$F10>=N$4),1,"") | ... R10: =IF(AND($E10<>"",$F10<>"",$E10<=R$4,$F10>=R$4),1,"")
A11: =WBS!A11 | B11: =WBS!C11 | C11: =WBS!D11 | D11: =WBS!F11 | E11: =WBS!G11 | F11: =WBS!I11 | G11: =IF(AND($E11<>"",$F11<>"",$E11<=G$4,$F11>=G$4),1,"") | H11: =IF(AND($E11<>"",$F11<>"",$E11<=H$4,$F11>=H$4),1,"") | I11: =IF(AND($E11<>"",$F11<>"",$E11<=I$4,$F11>=I$4),1,"") | J11: =IF(AND($E11<>"",$F11<>"",$E11<=J$4,$F11>=J$4),1,"") | K11: =IF(AND($E11<>"",$F11<>"",$E11<=K$4,$F11>=K$4),1,"") | L11: =IF(AND($E11<>"",$F11<>"",$E11<=L$4,$F11>=L$4),1,"") | M11: =IF(AND($E11<>"",$F11<>"",$E11<=M$4,$F11>=M$4),1,"") | N11: =IF(AND($E11<>"",$F11<>"",$E11<=N$4,$F11>=N$4),1,"") | ... R11: =IF(AND($E11<>"",$F11<>"",$E11<=R$4,$F11>=R$4),1,"")
A12: =WBS!A12 | B12: =WBS!C12 | C12: =WBS!D12 | D12: =WBS!F12 | E12: =WBS!G12 | F12: =WBS!I12 | G12: =IF(AND($E12<>"",$F12<>"",$E12<=G$4,$F12>=G$4),1,"") | H12: =IF(AND($E12<>"",$F12<>"",$E12<=H$4,$F12>=H$4),1,"") | I12: =IF(AND($E12<>"",$F12<>"",$E12<=I$4,$F12>=I$4),1,"") | J12: =IF(AND($E12<>"",$F12<>"",$E12<=J$4,$F12>=J$4),1,"") | K12: =IF(AND($E12<>"",$F12<>"",$E12<=K$4,$F12>=K$4),1,"") | L12: =IF(AND($E12<>"",$F12<>"",$E12<=L$4,$F12>=L$4),1,"") | M12: =IF(AND($E12<>"",$F12<>"",$E12<=M$4,$F12>=M$4),1,"") | N12: =IF(AND($E12<>"",$F12<>"",$E12<=N$4,$F12>=N$4),1,"") | ... R12: =IF(AND($E12<>"",$F12<>"",$E12<=R$4,$F12>=R$4),1,"")
A13: =WBS!A13 | B13: =WBS!C13 | C13: =WBS!D13 | D13: =WBS!F13 | E13: =WBS!G13 | F13: =WBS!I13 | G13: =IF(AND($E13<>"",$F13<>"",$E13<=G$4,$F13>=G$4),1,"") | H13: =IF(AND($E13<>"",$F13<>"",$E13<=H$4,$F13>=H$4),1,"") | I13: =IF(AND($E13<>"",$F13<>"",$E13<=I$4,$F13>=I$4),1,"") | J13: =IF(AND($E13<>"",$F13<>"",$E13<=J$4,$F13>=J$4),1,"") | K13: =IF(AND($E13<>"",$F13<>"",$E13<=K$4,$F13>=K$4),1,"") | L13: =IF(AND($E13<>"",$F13<>"",$E13<=L$4,$F13>=L$4),1,"") | M13: =IF(AND($E13<>"",$F13<>"",$E13<=M$4,$F13>=M$4),1,"") | N13: =IF(AND($E13<>"",$F13<>"",$E13<=N$4,$F13>=N$4),1,"") | ... R13: =IF(AND($E13<>"",$F13<>"",$E13<=R$4,$F13>=R$4),1,"")
A14: =WBS!A14 | B14: =WBS!C14 | C14: =WBS!D14 | D14: =WBS!F14 | E14: =WBS!G14 | F14: =WBS!I14 | G14: =IF(AND($E14<>"",$F14<>"",$E14<=G$4,$F14>=G$4),1,"") | H14: =IF(AND($E14<>"",$F14<>"",$E14<=H$4,$F14>=H$4),1,"") | I14: =IF(AND($E14<>"",$F14<>"",$E14<=I$4,$F14>=I$4),1,"") | J14: =IF(AND($E14<>"",$F14<>"",$E14<=J$4,$F14>=J$4),1,"") | K14: =IF(AND($E14<>"",$F14<>"",$E14<=K$4,$F14>=K$4),1,"") | L14: =IF(AND($E14<>"",$F14<>"",$E14<=L$4,$F14>=L$4),1,"") | M14: =IF(AND($E14<>"",$F14<>"",$E14<=M$4,$F14>=M$4),1,"") | N14: =IF(AND($E14<>"",$F14<>"",$E14<=N$4,$F14>=N$4),1,"") | ... R14: =IF(AND($E14<>"",$F14<>"",$E14<=R$4,$F14>=R$4),1,"")
A15: =WBS!A15 | B15: =WBS!C15 | C15: =WBS!D15 | D15: =WBS!F15 | E15: =WBS!G15 | F15: =WBS!I15 | G15: =IF(AND($E15<>"",$F15<>"",$E15<=G$4,$F15>=G$4),1,"") | H15: =IF(AND($E15<>"",$F15<>"",$E15<=H$4,$F15>=H$4),1,"") | I15: =IF(AND($E15<>"",$F15<>"",$E15<=I$4,$F15>=I$4),1,"") | J15: =IF(AND($E15<>"",$F15<>"",$E15<=J$4,$F15>=J$4),1,"") | K15: =IF(AND($E15<>"",$F15<>"",$E15<=K$4,$F15>=K$4),1,"") | L15: =IF(AND($E15<>"",$F15<>"",$E15<=L$4,$F15>=L$4),1,"") | M15: =IF(AND($E15<>"",$F15<>"",$E15<=M$4,$F15>=M$4),1,"") | N15: =IF(AND($E15<>"",$F15<>"",$E15<=N$4,$F15>=N$4),1,"") | ... R15: =IF(AND($E15<>"",$F15<>"",$E15<=R$4,$F15>=R$4),1,"")
A16: =WBS!A16 | B16: =WBS!C16 | C16: =WBS!D16 | D16: =WBS!F16 | E16: =WBS!G16 | F16: =WBS!I16 | G16: =IF(AND($E16<>"",$F16<>"",$E16<=G$4,$F16>=G$4),1,"") | H16: =IF(AND($E16<>"",$F16<>"",$E16<=H$4,$F16>=H$4),1,"") | I16: =IF(AND($E16<>"",$F16<>"",$E16<=I$4,$F16>=I$4),1,"") | J16: =IF(AND($E16<>"",$F16<>"",$E16<=J$4,$F16>=J$4),1,"") | K16: =IF(AND($E16<>"",$F16<>"",$E16<=K$4,$F16>=K$4),1,"") | L16: =IF(AND($E16<>"",$F16<>"",$E16<=L$4,$F16>=L$4),1,"") | M16: =IF(AND($E16<>"",$F16<>"",$E16<=M$4,$F16>=M$4),1,"") | N16: =IF(AND($E16<>"",$F16<>"",$E16<=N$4,$F16>=N$4),1,"") | ... R16: =IF(AND($E16<>"",$F16<>"",$E16<=R$4,$F16>=R$4),1,"")
A17: =WBS!A17 | B17: =WBS!C17 | C17: =WBS!D17 | D17: =WBS!F17 | E17: =WBS!G17 | F17: =WBS!I17 | G17: =IF(AND($E17<>"",$F17<>"",$E17<=G$4,$F17>=G$4),1,"") | H17: =IF(AND($E17<>"",$F17<>"",$E17<=H$4,$F17>=H$4),1,"") | I17: =IF(AND($E17<>"",$F17<>"",$E17<=I$4,$F17>=I$4),1,"") | J17: =IF(AND($E17<>"",$F17<>"",$E17<=J$4,$F17>=J$4),1,"") | K17: =IF(AND($E17<>"",$F17<>"",$E17<=K$4,$F17>=K$4),1,"") | L17: =IF(AND($E17<>"",$F17<>"",$E17<=L$4,$F17>=L$4),1,"") | M17: =IF(AND($E17<>"",$F17<>"",$E17<=M$4,$F17>=M$4),1,"") | N17: =IF(AND($E17<>"",$F17<>"",$E17<=N$4,$F17>=N$4),1,"") | ... R17: =IF(AND($E17<>"",$F17<>"",$E17<=R$4,$F17>=R$4),1,"")
A18: Fasi attive nella settimana | G18: =COUNT(G6:G17) | H18: =COUNT(H6:H17) | I18: =COUNT(I6:I17) | J18: =COUNT(J6:J17) | K18: =COUNT(K6:K17) | L18: =COUNT(L6:L17) | M18: =COUNT(M6:M17) | N18: =COUNT(N6:N17) | ... R18: =COUNT(R6:R17)
A20: Settimane con più di una fase attiva in parallelo | F20: =COUNTIF(G18:R18,">1")
A21: Settimana di massima concentrazione (n. fasi in parallelo) | F21: =MAX(G18:R18)

Sheet Riepilogo
A1: › RIEPILOGO DI PROGETTO
A2: Tutti i valori sono calcolati dalla WBS e dai Parametri. Nessuna cella di questo foglio va compilata a mano.
A4: › IMPEGNO E COSTO COMPLESSIVO
A5: Giornate front office (presso il cliente) | C5: =WBS!S18 | D5: gg-uomo
A6: Giornate back office | C6: =WBS!T18 | D6: gg-uomo
A7: Giornate di viaggio | C7: =WBS!U18 | D7: gg-uomo | E7: Incluse nel monte ore, come da impostazione concordata.
A8: TOTALE giornate-uomo di progetto | C8: =WBS!W18 | D8: gg-uomo
A9: TOTALE ore di progetto | C9: =WBS!X18 | D9: h | E9: Totale giornate × ore per giornata (Parametri!$C$5).
A10: COSTO TOTALE DI PROGETTO | C10: =WBS!Y18 | D10: €
A12: › RIPARTIZIONE DEL COSTO PER TIPOLOGIA DI ORA
A13: Costo ore front office | C13: =WBS!S18*Parametri!$C$5*Parametri!$C$6 | D13: €
A14: Costo ore back office | C14: =WBS!T18*Parametri!$C$5*Parametri!$C$7 | D14: €
A15: Costo ore di viaggio | C15: =WBS!U18*Parametri!$C$5*Parametri!$C$8 | D15: €
A16: Quadratura (deve coincidere con il costo totale) | C16: =SUM(C13:C15) | D16: € | E16: Controllo interno: se differisce dal costo totale c'è un errore di formula.
A18: › RIPARTIZIONE PER TIPO DI FASE
A19: Giornate — fasi con il cliente | C19: =SUMIF(WBS!$D$6:$D$17,"Cliente",WBS!$W$6:$W$17) | D19: gg-uomo
A20: Giornate — fasi interne | C20: =SUMIF(WBS!$D$6:$D$17,"Interna",WBS!$W$6:$W$17) | D20: gg-uomo
A21: Costo — fasi con il cliente | C21: =SUMIF(WBS!$D$6:$D$17,"Cliente",WBS!$Y$6:$Y$17) | D21: €
A22: Costo — fasi interne | C22: =SUMIF(WBS!$D$6:$D$17,"Interna",WBS!$Y$6:$Y$17) | D22: €
A23: Incontri previsti con il cliente | C23: =SUMIF(WBS!$D$6:$D$17,"Cliente",WBS!$Q$6:$Q$17) | D23: n.
A24: Fasi con il cliente / fasi interne | C24: =COUNTIF(WBS!$D$6:$D$17,"Cliente")&" / "&COUNTIF(WBS!$D$6:$D$17,"Interna")
A26: › LEAD TIME E EFFETTO DELLA PARALLELIZZAZIONE
A27: Somma delle durate delle fasi, se svolte in sequenza | C27: =SUM(WBS!H6:H17) | D27: settimane | E27: Somma aritmetica della colonna «Durata (sett.)» della WBS.
A28: Lead time di calendario effettivo | C28: =MAX(WBS!I6:I17)-MIN(WBS!G6:G17)+1 | D28: settimane | E28: Prima settimana di inizio → ultima settimana di fine, tenendo conto delle fasi sovrapposte.
A29: Settimane recuperate dalla parallelizzazione | C29: =C27-C28 | D29: settimane | E29: Effetto dei workshop svolti nelle stesse due settimane.
A30: Lead time target dichiarato | C30: =Parametri!$C$10 | D30: settimane | E30: Impostato nel foglio «Parametri».
A31: SCOSTAMENTO effettivo vs target | C31: =C28-C30 | D31: settimane | E31: Zero = il piano quadra. Se lo scostamento non è zero la cella si inverte in nero.
A32: Esito del controllo | C32: =IF(C28=C30,"Il piano quadra con il lead time target.","NON QUADRA — rivedere le settimane di inizio e le durate nella WBS.")
A34: › IPOTESI E PUNTI APERTI
A35: Pianificazione delle settimane | C35: Il piano proposto è: S1 kick off · S2 analisi dati · S3–S4 i cinque workshop con il cliente in parallelo (revenue model, ICP e customer journey, process design, tech stack, data model) · S5 interviste qualitative a valle del process design · S6 sintesi e business case · S7 review con il cliente · S8–S9 consolidamento report · S10 presentazione. Totale 10 settimane, coerente con il target dichiarato.
A36: Giornate front / back / viaggio | C36: Non ancora fornite: le celle sono vuote, sotto intestazione gialla. Finché non sono compilate, ore e costi restano a zero.
A37: Tariffe orarie | C37: Non ancora fornite: da inserire nel foglio «Parametri». Sono tre tariffe distinte (front, back, viaggio).
A38: Durata dei workshop | C38: Da definire per revenue model, ICP e customer journey, process design, tech stack, data model e presentazione finale (colonna «Durata incontro (h)» della WBS).
A39: Modalità da confermare | C39: Tech stack, data model e presentazione finale sono impostati su «Da definire»: da scegliere fra presenza e remoto. La scelta incide sulle giornate di viaggio.
A40: Somma sequenziale vs lead time | C40: La somma delle durate di fase vale 18 settimane perché le cinque fasi in parallelo occupano ciascuna la stessa finestra di 2 settimane. Il lead time reale resta 10 settimane: è questo il numero da leggere.
A41: Identità visiva | C41: Palette Impresoft di tre colori (giallo #FDC300, nero, bianco) più grigi puri derivati dal nero. Font Manrope, fallback Arial. Nessun colore semantico: verde e rosso sono stati sostituiti dalla scala monocroma e da etichette in parole.

Sheet Sheet

Sheet Parametri
A1: › PARAMETRI DI CALCOLO
A2: Le celle con riquadro nero, sotto l'intestazione gialla, sono da compilare. Tutto il resto del file si ricalcola da qui: modificando un valore in questa pagina si aggiornano ore e costi di tutte le fasi.
A4: Parametro | C4: Valore | D4: Unità | E4: Note
A5: Ore per giornata | C5: 8 | D5: h | E5: Base di conversione giornate → ore. Confermato: 8 ore.
A6: Tariffa oraria — Front office | D6: €/h | E6: Ore erogate presso il cliente.
A7: Tariffa oraria — Back office | D7: €/h | E7: Ore di lavoro interno (analisi, delivery, reportistica).
A8: Tariffa oraria — Viaggio | D8: €/h | E8: Ore di trasferimento. Incluse nel monte ore complessivo di progetto.
A10: Lead time target di progetto | C10: 10 | D10: settimane | E10: Durata di calendario dichiarata in fase di impostazione.
A12: Riferimenti usati dalle formule
A13: Ore per giornata = Parametri!$C$5 · Tariffe = $C$6 / $C$7 / $C$8 · Lead time target = $C$10

Sheet Ruoli
A1: › TEAM DI PROGETTO — RUOLI E NOMI
A2: Compilare la colonna Nome. I ruoli sono quelli richiamati nelle colonne Owner e Partecipanti della WBS.
A4: Ruolo | B4: Nome | C4: Seniority | D4: Presidio | E4: Note
A5: Commerciale | C5: Senior | D5: Fase 1 — convocazione kick off | E5: Invia la prima email al cliente per fissare il kick off.
A6: Project Manager | C6: Senior | D6: Fasi 1 → 12 — presidio di progetto | E6: Invia il follow-up post kick off con documento presentato e tracciato dati. Owner del piano.
A7: Facilitatore senior | B7: Alessandro Bruti | C7: Senior | D7: Tutti i workshop con il cliente | E7: Conduce i workshop di revenue model, ICP, process design, tech stack e data model.
A8: Consulente RevOps junior 1 | C8: Junior | D8: Workshop + back office | E8: In presenza ai workshop; analisi dati e compilazione file di delivery.
A9: Consulente RevOps junior 2 | C9: Junior | D9: Workshop + back office | E9: In presenza ai workshop; supporto alla delivery.
